{
  "name": "Дело №005 · Последняя Выставка",
  "truth": {
    "curator": "arundel",
    "motive": "revenge",
    "exit": "basement"
  },
  "start": "e0",
  "total": 16,
  "endings": {
    "win": {
      "mark": "✓",
      "verdict": "ЗАНАВЕС",
      "text": "Аранделл, месть, подвал — всё совпало. Гости спасены. Куратор ушёл, но ты знаешь его лицо. Сдвиг, бледный от потери крови, протянул тебе значок: «Теперь ты агент, а не рекрут. Охота продолжается»."
    },
    "partial": {
      "mark": "≈",
      "verdict": "ВЫСТАВКА ЗАКРЫТА, ХУДОЖНИК НА СВОБОДЕ",
      "text": "Ты спас людей — это главное. Но Аранделл уже в другом городе. Он оставил перстень с буквой «А» на каминной полке. Специально для тебя."
    },
    "fail": {
      "mark": "✗",
      "verdict": "ФИНАЛЬНЫЙ АКТ НЕ СОСТОЯЛСЯ",
      "text": "Не тот гость, не тот мотив, не тот выход. Пока вы разбирались, настоящий Куратор сел в поезд. История продолжается без ответов."
    }
  },
  "events": {
    "e0": {
      "t": "crime",
      "badge": "Особняк",
      "title": "Гала-вечер",
      "text": "Январь 1988-го. Ежегодный благотворительный вечер в особняке Уилфорда. Сорок гостей, шампанское, картины. В 21:00 двери заперты изнутри. Голос через репродуктор: . Сдвиг ранен в первые минуты. Ты один",
      "left": {
        "label": "Обеспечить периметр",
        "to": "eL2c1"
      },
      "right": {
        "label": "К Сдвигу",
        "to": "eL2c1"
      },
      "dialogue": "Сдвиг: «Добро пожаловать на финальную выставку. Экспонаты — вы»",
      "speaker": "shift"
    },
    "eL2c1": {
      "t": "crime",
      "badge": "Большой зал",
      "title": "Живые экспонаты",
      "text": "Гости сбились в угол. Картины на стенах — все фальшивки. В каждой — маленькое клеймо: перевёрнутая . Три человека держатся особняком: Аранделл, Холлис, Торн",
      "left": {
        "label": "Осмотреть картины",
        "evidence": "Все подделки — работы художников, уничтоженных ФБР в 1983-м в ходе операции «Чистое искусство».",
        "to": "eL2c2"
      },
      "right": {
        "label": "Наблюдать за тремя",
        "evidence": "Аранделл — известный арт-критик. Холлис — галерист. Торн — страховой брокер. Все трое знали жертв из прежних дел.",
        "to": "eL2c2"
      },
      "dialogue": "К"
    },
    "eL2c2": {
      "t": "evidence",
      "badge": "Галерея",
      "title": "1983 год",
      "text": "Операция : ФБР уничтожило три семьи, причастные к рынку поддельных произведений. Официально — случайные жертвы. Неофициально — расходный материал",
      "left": {
        "label": "Найти связь",
        "evidence": "Среди пострадавших — семья Аранделлов. Отец — арт-дилер, погиб под следствием. Артур Аранделл тогда — 22 года.",
        "to": "eL2c3"
      },
      "right": {
        "label": "Проверить Холлиса",
        "evidence": "Холлис: алиби на все пять смертей. Чистый. Торн — аналогично. Аранделл — ни разу не проверялся.",
        "to": "eL2c3"
      },
      "dialogue": "Чистое искусство"
    },
    "eL2c3": {
      "t": "suspect",
      "badge": "Трое",
      "title": "Перстень с буквой А",
      "text": "В кармане Сдвига — перстень с буквой , снятый с руки человека в плаще в санатории. Среди троих — у одного нет кольца на правой руке",
      "left": {
        "label": "Проверить руки",
        "evidence": "Аранделл носит перстень на правой руке — сейчас пустое место. Бледная полоска кожи.",
        "to": "eShift1"
      },
      "right": {
        "label": "Задать прямой вопрос",
        "evidence": "Аранделл улыбается: «Потерял в лесу. Жаль — семейная реликвия». Пауза. Холодные глаза.",
        "to": "eShift1"
      },
      "dialogue": "А"
    },
    "eShift1": {
      "shift": true,
      "t": "shift",
      "badge": "СДВИГ · 1",
      "title": "Лицо Куратора",
      "intro": "Тридцать картин. Три человека. Одно пустое место на руке.",
      "a": {
        "label": "◄ ХОЛЛИС",
        "vtext": "Галерист — идеальное прикрытие. Он мог организовать все поставки и оставаться в тени.",
        "set": {
          "curator": "hollis"
        },
        "bad": true,
        "to": "eL2c4"
      },
      "b": {
        "label": "АРАНДЕЛЛ ►",
        "vtext": "Перстень, буква А, 1983 год, семья уничтожена ФБР — это не совпадение. Это биография.",
        "set": {
          "curator": "arundel"
        },
        "to": "eL2c4"
      }
    },
    "eL2c4": {
      "t": "revelation",
      "badge": "Мотив",
      "title": "Отец Аранделла",
      "text": "Сдвиг сквозь зубы",
      "left": {
        "label": "Слушать Сдвига",
        "to": "eL3c1"
      },
      "right": {
        "label": "Изучать досье",
        "to": "eL3c1"
      },
      "dialogue": "Сдвиг: «Его отца — Конрада Аранделла — мы закрыли в 83-м. Дело сфабриковано. Я это знал и молчал. Потому что так приказали»",
      "speaker": "shift"
    },
    "eL3c1": {
      "t": "evidence",
      "badge": "Библиотека",
      "title": "Досье на Конрада",
      "text": "В библиотеке особняка Аранделл оставил личное досье. Сверху — фотография: Конрад Аранделл в наручниках. Внизу — подпись",
      "left": {
        "label": "Читать досье",
        "evidence": "Конрад Аранделл был невиновен. Три агента ФБР сфабриковали доказательства. Двое из них — под прикрытием Сдвига.",
        "to": "eL3c2"
      },
      "right": {
        "label": "Искать Аранделла",
        "evidence": "Следов нет — только открытая дверь в конце коридора и запах сигары.",
        "to": "eL3c2"
      },
      "dialogue": "Настоящий экспонат"
    },
    "eL3c2": {
      "t": "suspect",
      "badge": "Выбор",
      "title": "Гости и Куратор",
      "text": "У Аранделла два пути: уйти в подвальный тоннель или остаться. Сорок гостей заперты. Ты один. Сдвиг без сознания.",
      "left": {
        "label": "Ищи Аранделла",
        "evidence": "Коридор. Открытая дверь в подвал. Звук шагов уходит вниз.",
        "to": "eL3c3"
      },
      "right": {
        "label": "К гостям",
        "evidence": "Гости паникуют. Кто-то бьётся об окно. Тридцать секунд — и будет жертва.",
        "to": "eL3c3"
      }
    },
    "eL3c3": {
      "t": "evidence",
      "badge": "Дилемма",
      "title": "Что важнее",
      "text": "Снизу — звук захлопнувшейся двери. Сверху — женский крик. Куратор это просчитал.",
      "left": {
        "label": "Вниз, за Куратором",
        "evidence": "Тоннель пуст. Пока ты спускался — наверху разбили стекло. Никто не пострадал, но Аранделл ушёл.",
        "to": "eShift2"
      },
      "right": {
        "label": "Наверх, к гостям",
        "evidence": "Все живы. Аранделл растворился. На каминной полке — записка: «Верный выбор, рекрут».",
        "to": "eShift2"
      }
    },
    "eShift2": {
      "shift": true,
      "t": "shift",
      "badge": "СДВИГ · 2",
      "title": "Что важнее — люди или правда",
      "intro": "Один выбор определяет, кто ты — охотник или защитник.",
      "a": {
        "label": "◄ ПОЙМАТЬ КУРАТОРА",
        "vtext": "Правда дороже. Аранделл — убийца, пусть и справедливо гневный.",
        "set": {
          "motive": "justice"
        },
        "bad": true,
        "to": "eL3c4"
      },
      "b": {
        "label": "СПАСТИ ГОСТЕЙ ►",
        "vtext": "Куратор уйдёт. Но сорок человек живут. И Аранделл это увидел — и оставил записку.",
        "set": {
          "motive": "revenge"
        },
        "to": "eL3c4"
      }
    },
    "eL3c4": {
      "t": "revelation",
      "badge": "Подвал",
      "title": "Тоннель Аранделла",
      "text": "В тоннеле — последнее послание",
      "left": {
        "label": "Идти в тоннель",
        "to": "eL4c1"
      },
      "right": {
        "label": "Осмотреть подвал",
        "to": "eL4c1"
      },
      "dialogue": "Куратор: «Я не убивал невиновных, рекрут. Только тех, кто уничтожал их. Счёт закрыт. Пока»",
      "speaker": "kurator"
    },
    "eL4c1": {
      "t": "evidence",
      "badge": "Выход",
      "title": "Путь Аранделла",
      "text": "Тоннель выходит в двух кварталах — у железнодорожной станции. Последний поезд ушёл восемь минут назад.",
      "left": {
        "label": "Искать следы",
        "evidence": "На перроне — окурок сигары и билет: направление запад. Один конец.",
        "to": "eL4c2"
      },
      "right": {
        "label": "Вернуться к Сдвигу",
        "evidence": "Сдвиг пришёл в себя. Смотрит на тебя. «Ты выбрал людей. Хорошо. Значит, ты не я».",
        "to": "eL4c2"
      }
    },
    "eL4c2": {
      "t": "evidence",
      "badge": "Рассвет",
      "title": "Значок",
      "text": "Сдвиг вытаскивает что-то из внутреннего кармана. Агентский значок — новый, на чистой бумаге. Кладёт перед тобой на стол.",
      "left": {
        "label": "Взять значок",
        "evidence": "Ты берёшь значок. Аранделл свободен. Охота продолжается.",
        "to": "eShift3"
      },
      "right": {
        "label": "Подождать",
        "evidence": "Сдвиг: «Есть сомнения? Это правильно. Сомневающийся агент живёт дольше».",
        "to": "eShift3"
      },
      "dialogue": "Сдвиг: «Ты выбрал людей. Значит, ты не я». — и протягивает значок.",
      "speaker": "shift"
    },
    "eShift3": {
      "shift": true,
      "t": "shift",
      "badge": "СДВИГ · 3",
      "title": "Кто ты теперь",
      "intro": "Последний сдвиг. Не по делу — по тебе самому.",
      "a": {
        "label": "◄ УЙТИ",
        "vtext": "ФБР скрывало правду. Аранделл был прав. Ты не можешь работать в системе, которая убивала невиновных.",
        "set": {
          "destiny": "quit"
        },
        "bad": true,
        "to": "eAccuse"
      },
      "b": {
        "label": "ОСТАТЬСЯ ►",
        "vtext": "Система гнилая — но Куратор на свободе. Менять правила можно только изнутри. Ты берёшь значок.",
        "set": {
          "destiny": "stay"
        },
        "to": "eAccuse"
      },
      "speaker": "shift"
    },
    "eAccuse": {
      "t": "final",
      "badge": "Финал кампании",
      "title": "Охота продолжается",
      "text": "Особняк пуст. Гости по домам. Сдвиг дымит в машине. Ты смотришь на значок в ладони. Аранделл — где-то на западе. Куратор никогда не было одно имя. Это была идея. А идеи не арестуют.",
      "left": {
        "label": "Закрыть дело",
        "set": {
          "end": "true"
        },
        "to": "__resolve__"
      },
      "right": {
        "label": "Оставить открытым",
        "set": {
          "end": "true"
        },
        "to": "__resolve__"
      },
      "dialogue": "Сдвиг: «Куратор никогда не было имя. Это идея. А идеи не арестуют».",
      "speaker": "arundel"
    }
  }
}